{
    "WBW_KRYPTO_DEJAVU": [
        {
            "Task_Progress": "100%",
            "Name": "WBM_150_v01-/sta",
            "Task_name": "WBM_150_v01 - /stage/submit/usdrender_rop",
            "User": "ushakova",
            "Plugin": "Houdini",
            "Progress": "25%",
            "Tasks": "(16/63)",
            "Status": "Rendering (43)",
            "Project": "WBW_KRYPTO_DEJAVU",
            "Render": "usdrender_rop",
            "est.": "00:05:09",
            "Priority": "60"
        }
    ],
    "AUTODESK_PRLM": [
        {
            "Task_Progress": "49%",
            "Name": "Daytime_Earth_v2",
            "Task_name": "Daytime_Earth_v20 - /out/main_steel_2",
            "User": "goncharov",
            "Plugin": "Houdini",
            "Progress": "49%",
            "Tasks": "(0/1)",
            "Status": "Rendering (1)",
            "Project": "AUTODESK_PRLM",
            "Render": "main_steel_2",
            "est.": "unknown",
            "Priority": "60"
        },
        {
            "Task_Progress": "13%",
            "Name": "Daytime_Earth_v2",
            "Task_name": "Daytime_Earth_v20 - /out/clouds_steel_2",
            "User": "goncharov",
            "Plugin": "Houdini",
            "Progress": "13%",
            "Tasks": "(0/1)",
            "Status": "Rendering (1)",
            "Project": "AUTODESK_PRLM",
            "Render": "clouds_steel_2",
            "est.": "unknown",
            "Priority": "60"
        },
        {
            "Task_Progress": "87%",
            "Name": "Daytime_Earth_v2",
            "Task_name": "Daytime_Earth_v20 - /out/clouds_steel_1",
            "User": "goncharov",
            "Plugin": "Houdini",
            "Progress": "87%",
            "Tasks": "(0/1)",
            "Status": "Rendering (1)",
            "Project": "AUTODESK_PRLM",
            "Render": "clouds_steel_1",
            "est.": "unknown",
            "Priority": "60"
        }
    ]
}