{
    "QIDDIYA_CHARLY": [
        {
            "Task_Progress": "100%",
            "Name": "Comedy_Stage_v04",
            "Task_name": "Comedy_Stage_v04 - /obj/lopnet1/main/usdrender_rop",
            "User": "veber",
            "Plugin": "Houdini",
            "Progress": "80%",
            "Tasks": "(202/250)",
            "Status": "Rendering (15)",
            "Project": "QIDDIYA_CHARLY",
            "Render": "usdrender_rop",
            "est.": "01:00:40",
            "Priority": "60"
        }
    ],
    "TUTORS": [
        {
            "Task_Progress": "100%",
            "Name": "Vellum_Scene_v03",
            "Task_name": "Vellum_Scene_v03 - /out/M_Fur",
            "User": "hozhaev",
            "Plugin": "Houdini",
            "Progress": "29%",
            "Tasks": "(725/2475)",
            "Status": "Rendering (38)",
            "Project": "TUTORS",
            "Render": "M_Fur",
            "est.": "06:16:19",
            "Priority": "60"
        }
    ]
}