{
    "AUTODESK_PRLM": [
        {
            "Task_Progress": "100%",
            "Name": "BND_0040_v06-/ob",
            "Task_name": "BND_0040_v06 - /obj/lopnet1/BND_0040/usdrender_rop",
            "User": "glavatskih",
            "Plugin": "Houdini",
            "Progress": "21%",
            "Tasks": "(9/41)",
            "Status": "Rendering (12)",
            "Project": "AUTODESK_PRLM",
            "Render": "usdrender_rop",
            "est.": "00:07:00",
            "Priority": "60"
        }
    ],
    "WBW_KRYPTO_DEJAVU": [
        {
            "Task_Progress": "100%",
            "Name": "WBC_100_v06-/out",
            "Task_name": "WBC_100_v06 - /out/nebulaz",
            "User": "ushakova",
            "Plugin": "Houdini",
            "Progress": "50%",
            "Tasks": "(1/2)",
            "Status": "Rendering (1)",
            "Project": "WBW_KRYPTO_DEJAVU",
            "Render": "nebulaz",
            "est.": "00:00:01",
            "Priority": "60"
        }
    ],
    "WINLINE_WORLDCUP": [
        {
            "Task_Progress": "100%",
            "Name": "WWC_HOLO_v42-/st",
            "Task_name": "WWC_HOLO_v42 - /stage/arcsSmoke/usdrender_rop",
            "User": "dmakarov",
            "Plugin": "Houdini",
            "Progress": "10%",
            "Tasks": "(53/500)",
            "Status": "Rendering (17)",
            "Project": "WINLINE_WORLDCUP",
            "Render": "usdrender_rop",
            "est.": "02:02:24",
            "Priority": "60"
        },
        {
            "Task_Progress": "100%",
            "Name": "WWC_HOLO_v42-/st",
            "Task_name": "WWC_HOLO_v42 - /stage/Shockwave/usdrender_rop",
            "User": "dmakarov",
            "Plugin": "Houdini",
            "Progress": "14%",
            "Tasks": "(71/500)",
            "Status": "Rendering (10)",
            "Project": "WINLINE_WORLDCUP",
            "Render": "usdrender_rop",
            "est.": "03:39:48",
            "Priority": "60"
        }
    ]
}