{
    "WBW_KRYPTO_DEJAVU": [
        {
            "Task_Progress": "100%",
            "Name": "WBC_100_v20-/out",
            "Task_name": "WBC_100_v20 - /out/vol",
            "User": "mochalova",
            "Plugin": "Houdini",
            "Progress": "93%",
            "Tasks": "(78/83)",
            "Status": "Rendering (5)",
            "Project": "WBW_KRYPTO_DEJAVU",
            "Render": "vol",
            "est.": "00:00:01",
            "Priority": "70"
        },
        {
            "Task_Progress": "0%",
            "Name": "WBC_100_v20-/out",
            "Task_name": "WBC_100_v20 - /out/car",
            "User": "mochalova",
            "Plugin": "Houdini",
            "Progress": "0%",
            "Tasks": "(0/83)",
            "Status": "Rendering (3)",
            "Project": "WBW_KRYPTO_DEJAVU",
            "Render": "car",
            "est.": "unknown",
            "Priority": "70"
        },
        {
            "Task_Progress": "100%",
            "Name": "WBC_100_comp_sta",
            "Task_name": "WBC_100_comp_stavile_v19.nk",
            "User": "stavile",
            "Plugin": "Nuke",
            "Progress": "76%",
            "Tasks": "(13/17)",
            "Status": "Rendering (4)",
            "Project": "WBW_KRYPTO_DEJAVU",
            "Render": "WBC_100_comp_stavile_v19.nk",
            "est.": "00:00:01",
            "Priority": "90"
        }
    ],
    "SCANIA_BK": [
        {
            "Task_Progress": "100%",
            "Name": "Holo_v30-/out/al",
            "Task_name": "Holo_v30 - /out/all_all_Frame",
            "User": "dmakarov",
            "Plugin": "Houdini",
            "Progress": "49%",
            "Tasks": "(62/125)",
            "Status": "Rendering (5)",
            "Project": "SCANIA_BK",
            "Render": "all_all_Frame",
            "est.": "00:53:48",
            "Priority": "60"
        },
        {
            "Task_Progress": "100%",
            "Name": "Holo_v30-/out/Vo",
            "Task_name": "Holo_v30 - /out/VoxelsFullFrame",
            "User": "dmakarov",
            "Plugin": "Houdini",
            "Progress": "32%",
            "Tasks": "(40/125)",
            "Status": "Rendering (4)",
            "Project": "SCANIA_BK",
            "Render": "VoxelsFullFrame",
            "est.": "02:20:42",
            "Priority": "60"
        },
        {
            "Task_Progress": "100%",
            "Name": "Holo_v30-/out/Co",
            "Task_name": "Holo_v30 - /out/CoverFullFrame",
            "User": "dmakarov",
            "Plugin": "Houdini",
            "Progress": "66%",
            "Tasks": "(83/125)",
            "Status": "Rendering (4)",
            "Project": "SCANIA_BK",
            "Render": "CoverFullFrame",
            "est.": "00:31:36",
            "Priority": "60"
        },
        {
            "Task_Progress": "100%",
            "Name": "Holo_v29-/out/Pa",
            "Task_name": "Holo_v29 - /out/PatternFullFrame",
            "User": "dmakarov",
            "Plugin": "Houdini",
            "Progress": "68%",
            "Tasks": "(86/125)",
            "Status": "Rendering (5)",
            "Project": "SCANIA_BK",
            "Render": "PatternFullFrame",
            "est.": "00:21:51",
            "Priority": "60"
        },
        {
            "Task_Progress": "100%",
            "Name": "Holo_v29-/out/Co",
            "Task_name": "Holo_v29 - /out/CoverFullFrame",
            "User": "dmakarov",
            "Plugin": "Houdini",
            "Progress": "74%",
            "Tasks": "(93/125)",
            "Status": "Rendering (5)",
            "Project": "SCANIA_BK",
            "Render": "CoverFullFrame",
            "est.": "00:18:47",
            "Priority": "60"
        },
        {
            "Task_Progress": "100%",
            "Name": "Holo_v29-/out/Co",
            "Task_name": "Holo_v29 - /out/ContuorFullFrame",
            "User": "dmakarov",
            "Plugin": "Houdini",
            "Progress": "86%",
            "Tasks": "(108/125)",
            "Status": "Rendering (5)",
            "Project": "SCANIA_BK",
            "Render": "ContuorFullFrame",
            "est.": "00:06:49",
            "Priority": "60"
        },
        {
            "Task_Progress": "100%",
            "Name": "Holo_v29-/out/Vo",
            "Task_name": "Holo_v29 - /out/VoxelsFullFrame",
            "User": "dmakarov",
            "Plugin": "Houdini",
            "Progress": "40%",
            "Tasks": "(50/125)",
            "Status": "Rendering (5)",
            "Project": "SCANIA_BK",
            "Render": "VoxelsFullFrame",
            "est.": "01:27:42",
            "Priority": "60"
        },
        {
            "Task_Progress": "100%",
            "Name": "Holo_v30-/out/Pa",
            "Task_name": "Holo_v30 - /out/PatternFullFrame",
            "User": "dmakarov",
            "Plugin": "Houdini",
            "Progress": "76%",
            "Tasks": "(96/125)",
            "Status": "Rendering (4)",
            "Project": "SCANIA_BK",
            "Render": "PatternFullFrame",
            "est.": "00:18:47",
            "Priority": "60"
        },
        {
            "Task_Progress": "100%",
            "Name": "Holo_v29-/out/Co",
            "Task_name": "Holo_v29 - /out/ContuorBackFrame",
            "User": "dmakarov",
            "Plugin": "Houdini",
            "Progress": "83%",
            "Tasks": "(104/125)",
            "Status": "Rendering (5)",
            "Project": "SCANIA_BK",
            "Render": "ContuorBackFrame",
            "est.": "00:07:29",
            "Priority": "60"
        },
        {
            "Task_Progress": "100%",
            "Name": "Holo_v29-/out/al",
            "Task_name": "Holo_v29 - /out/all_all_Frame",
            "User": "dmakarov",
            "Plugin": "Houdini",
            "Progress": "42%",
            "Tasks": "(53/125)",
            "Status": "Rendering (5)",
            "Project": "SCANIA_BK",
            "Render": "all_all_Frame",
            "est.": "01:25:13",
            "Priority": "60"
        },
        {
            "Task_Progress": "100%",
            "Name": "Holo_v30-/out/Co",
            "Task_name": "Holo_v30 - /out/ContuorFullFrame",
            "User": "dmakarov",
            "Plugin": "Houdini",
            "Progress": "73%",
            "Tasks": "(92/125)",
            "Status": "Rendering (6)",
            "Project": "SCANIA_BK",
            "Render": "ContuorFullFrame",
            "est.": "00:11:34",
            "Priority": "60"
        },
        {
            "Task_Progress": "100%",
            "Name": "Holo_v30-/out/Co",
            "Task_name": "Holo_v30 - /out/ContuorFrontFrame",
            "User": "dmakarov",
            "Plugin": "Houdini",
            "Progress": "92%",
            "Tasks": "(115/125)",
            "Status": "Rendering (4)",
            "Project": "SCANIA_BK",
            "Render": "ContuorFrontFrame",
            "est.": "00:03:28",
            "Priority": "60"
        }
    ],
    "NJM_SPOTLIGHT_PRLM": [
        {
            "Task_Progress": "100%",
            "Name": "SPO_110_comp_v03",
            "Task_name": "SPO_110_comp_v03.nk",
            "User": "shkrabo",
            "Plugin": "Nuke",
            "Progress": "10%",
            "Tasks": "(2/19)",
            "Status": "Rendering (11)",
            "Project": "NJM_SPOTLIGHT_PRLM",
            "Render": "SPO_110_comp_v03.nk",
            "est.": "00:00:37",
            "Priority": "90"
        }
    ],
    "SIDE_MISSIONS_BK": [
        {
            "Task_Progress": "100%",
            "Name": "Side_Missions_BK",
            "Task_name": "Side_Missions_BK_lookdev_Wrathog_v008 - /stage/main_rop",
            "User": "kufterin",
            "Plugin": "Houdini",
            "Progress": "65%",
            "Tasks": "(65/100)",
            "Status": "Rendering (1)",
            "Project": "SIDE_MISSIONS_BK",
            "Render": "main_rop",
            "est.": "02:37:16",
            "Priority": "60"
        }
    ],
    "AUTODESK_PRLM": [
        {
            "Task_Progress": "0%",
            "Name": "BND_0130_comp_v0",
            "Task_name": "BND_0130_comp_v01.nk",
            "User": "lukyanova",
            "Plugin": "Nuke",
            "Progress": "0%",
            "Tasks": "(0/8)",
            "Status": "Queued",
            "Project": "AUTODESK_PRLM",
            "Render": "BND_0130_comp_v01.nk",
            "est.": "00:00:00",
            "Priority": "90"
        }
    ]
}