{
    "TUTORS": [
        {
            "Task_Progress": "55%",
            "Name": "Vellum_Scene_v03",
            "Task_name": "Vellum_Scene_v03 - /obj/Construct/Fur_L_cch/render",
            "User": "hozhaev",
            "Plugin": "Houdini",
            "Progress": "55%",
            "Tasks": "(0/1)",
            "Status": "Rendering (1)",
            "Project": "TUTORS",
            "Render": "render",
            "est.": "unknown",
            "Priority": "100"
        }
    ]
}