{
    "AUTODESK_PRLM": [
        {
            "Task_Progress": "100%",
            "Name": "Daytime_Earth_v0",
            "Task_name": "Daytime_Earth_v04 - /out/CLOUDS",
            "User": "goncharov",
            "Plugin": "Houdini",
            "Progress": "20%",
            "Tasks": "(9/45)",
            "Status": "Rendering (4)",
            "Project": "AUTODESK_PRLM",
            "Render": "CLOUDS",
            "est.": "00:08:58",
            "Priority": "60"
        },
        {
            "Task_Progress": "100%",
            "Name": "Nighttime_Earth_",
            "Task_name": "Nighttime_Earth_v02 - /out/atmo",
            "User": "goncharov",
            "Plugin": "Houdini",
            "Progress": "26%",
            "Tasks": "(12/45)",
            "Status": "Rendering (2)",
            "Project": "AUTODESK_PRLM",
            "Render": "atmo",
            "est.": "00:08:20",
            "Priority": "60"
        },
        {
            "Task_Progress": "100%",
            "Name": "Daytime_Earth_v0",
            "Task_name": "Daytime_Earth_v04 - /out/main",
            "User": "goncharov",
            "Plugin": "Houdini",
            "Progress": "11%",
            "Tasks": "(5/45)",
            "Status": "Rendering (1)",
            "Project": "AUTODESK_PRLM",
            "Render": "main",
            "est.": "00:27:57",
            "Priority": "60"
        },
        {
            "Task_Progress": "100%",
            "Name": "Nighttime_Earth_",
            "Task_name": "Nighttime_Earth_v02 - /out/main",
            "User": "goncharov",
            "Plugin": "Houdini",
            "Progress": "13%",
            "Tasks": "(6/45)",
            "Status": "Rendering (3)",
            "Project": "AUTODESK_PRLM",
            "Render": "main",
            "est.": "00:07:43",
            "Priority": "60"
        },
        {
            "Task_Progress": "100%",
            "Name": "Nighttime_Earth_",
            "Task_name": "Nighttime_Earth_v02 - /out/CLOUDS",
            "User": "goncharov",
            "Plugin": "Houdini",
            "Progress": "13%",
            "Tasks": "(6/45)",
            "Status": "Rendering (2)",
            "Project": "AUTODESK_PRLM",
            "Render": "CLOUDS",
            "est.": "00:16:14",
            "Priority": "60"
        },
        {
            "Task_Progress": "100%",
            "Name": "Daytime_Earth_v0",
            "Task_name": "Daytime_Earth_v04 - /out/atmo",
            "User": "goncharov",
            "Plugin": "Houdini",
            "Progress": "55%",
            "Tasks": "(25/45)",
            "Status": "Rendering (3)",
            "Project": "AUTODESK_PRLM",
            "Render": "atmo",
            "est.": "00:03:11",
            "Priority": "60"
        }
    ],
    "MAGNIT_ICE_ROCS": [
        {
            "Task_Progress": "100%",
            "Name": "BNK_010_v15-/out",
            "Task_name": "BNK_010_v15 - /out/melon",
            "User": "shashkov",
            "Plugin": "Houdini",
            "Progress": "60%",
            "Tasks": "(59/97)",
            "Status": "Rendering (21)",
            "Project": "MAGNIT_ICE_ROCS",
            "Render": "melon",
            "est.": "00:01:23",
            "Priority": "60"
        },
        {
            "Task_Progress": "100%",
            "Name": "BNK_010_v15-/out",
            "Task_name": "BNK_010_v15 - /out/grape",
            "User": "shashkov",
            "Plugin": "Houdini",
            "Progress": "64%",
            "Tasks": "(63/97)",
            "Status": "Rendering (21)",
            "Project": "MAGNIT_ICE_ROCS",
            "Render": "grape",
            "est.": "00:01:05",
            "Priority": "60"
        }
    ],
    "SUMMER_CLASSIC_JOZI": [
        {
            "Task_Progress": "100%",
            "Name": "TST015_51326_04",
            "Task_name": "TST015_51326_04",
            "User": "hozhaev",
            "Progress": "97%",
            "Tasks": "(70/72)",
            "Status": "Rendering (2)",
            "Project": "SUMMER_CLASSIC_JOZI",
            "Render": "TST015_51326_04",
            "est.": "00:00:01",
            "Priority": "60"
        }
    ]
}