{
    "WINLINE_WORLDCUP": [
        {
            "Task_Progress": "100%",
            "Name": "stad_sh05_v09-/s",
            "Task_name": "stad_sh05_v09 - /stage/crowd_fg/usdrender_rop",
            "User": "aleksandrov",
            "Plugin": "Houdini",
            "Progress": "31%",
            "Tasks": "(58/185)",
            "Status": "Rendering (10)",
            "Project": "WINLINE_WORLDCUP",
            "Render": "usdrender_rop",
            "est.": "01:15:31",
            "Priority": "60"
        },
        {
            "Task_Progress": "100%",
            "Name": "stad_sh05_v09-/s",
            "Task_name": "stad_sh05_v09 - /stage/crowd_bg/usdrender_rop",
            "User": "aleksandrov",
            "Plugin": "Houdini",
            "Progress": "34%",
            "Tasks": "(63/185)",
            "Status": "Rendering (10)",
            "Project": "WINLINE_WORLDCUP",
            "Render": "usdrender_rop",
            "est.": "01:06:13",
            "Priority": "60"
        },
        {
            "Task_Progress": "100%",
            "Name": "stad_sh05_v09-/s",
            "Task_name": "stad_sh05_v09 - /stage/ground1/usdrender_rop",
            "User": "aleksandrov",
            "Plugin": "Houdini",
            "Progress": "69%",
            "Tasks": "(129/185)",
            "Status": "Rendering (10)",
            "Project": "WINLINE_WORLDCUP",
            "Render": "usdrender_rop",
            "est.": "00:12:06",
            "Priority": "60"
        },
        {
            "Task_Progress": "100%",
            "Name": "stad_sh05_v09-/s",
            "Task_name": "stad_sh05_v09 - /stage/flags/usdrender_rop",
            "User": "aleksandrov",
            "Plugin": "Houdini",
            "Progress": "16%",
            "Tasks": "(30/185)",
            "Status": "Rendering (9)",
            "Project": "WINLINE_WORLDCUP",
            "Render": "usdrender_rop",
            "est.": "01:51:06",
            "Priority": "60"
        },
        {
            "Task_Progress": "100%",
            "Name": "stad_sh05_v09-/s",
            "Task_name": "stad_sh05_v09 - /stage/volum/usdrender_rop",
            "User": "aleksandrov",
            "Plugin": "Houdini",
            "Progress": "56%",
            "Tasks": "(105/185)",
            "Status": "Rendering (10)",
            "Project": "WINLINE_WORLDCUP",
            "Render": "usdrender_rop",
            "est.": "00:15:37",
            "Priority": "60"
        },
        {
            "Task_Progress": "100%",
            "Name": "stad_sh05_v09-/s",
            "Task_name": "stad_sh05_v09 - /stage/main1/usdrender_rop",
            "User": "aleksandrov",
            "Plugin": "Houdini",
            "Progress": "44%",
            "Tasks": "(83/185)",
            "Status": "Rendering (8)",
            "Project": "WINLINE_WORLDCUP",
            "Render": "usdrender_rop",
            "est.": "00:41:01",
            "Priority": "60"
        }
    ]
}