{
    "MAGNIT_ICE_ROCS": [
        {
            "Task_Progress": "100%",
            "Name": "MAR_020_v25-/out",
            "Task_name": "MAR_020_v25 - /out/hero",
            "User": "shashkov",
            "Plugin": "Houdini",
            "Progress": "91%",
            "Tasks": "(57/62)",
            "Status": "Rendering (5)",
            "Project": "MAGNIT_ICE_ROCS",
            "Render": "hero",
            "est.": "00:00:01",
            "Priority": "60"
        }
    ]
}