{
    "CFI_DJV": [
        {
            "Task_Progress": "100%",
            "Name": "CFD_010_v16-/out",
            "Task_name": "CFD_010_v16 - /out/main",
            "User": "gridasov",
            "Plugin": "Houdini",
            "Progress": "34%",
            "Tasks": "(96/277)",
            "Status": "Rendering (10)",
            "Project": "CFI_DJV",
            "Render": "main",
            "est.": "02:06:03",
            "Priority": "60"
        }
    ],
    "T2_INSTRUCTION": [
        {
            "Task_Progress": "100%",
            "Name": "TTI_047_comp_v02",
            "Task_name": "TTI_047_comp_v02.nk",
            "User": "a.ivanov",
            "Plugin": "Nuke",
            "Progress": "16%",
            "Tasks": "(5/31)",
            "Status": "Rendering (6)",
            "Project": "T2_INSTRUCTION",
            "Render": "TTI_047_comp_v02.nk",
            "est.": "00:02:20",
            "Priority": "90"
        },
        {
            "Task_Progress": "100%",
            "Name": "TTI_005_comp_doo",
            "Task_name": "TTI_005_comp_dooh_6sec_v36.nk",
            "User": "lebedevich",
            "Plugin": "Nuke",
            "Progress": "86%",
            "Tasks": "(33/38)",
            "Status": "Rendering (5)",
            "Project": "T2_INSTRUCTION",
            "Render": "TTI_005_comp_dooh_6sec_v36.nk",
            "est.": "00:00:01",
            "Priority": "90"
        },
        {
            "Task_Progress": "100%",
            "Name": "TTI_005_comp_doo",
            "Task_name": "TTI_005_comp_dooh_6sec_v35.nk",
            "User": "lebedevich",
            "Plugin": "Nuke",
            "Progress": "86%",
            "Tasks": "(33/38)",
            "Status": "Rendering (5)",
            "Project": "T2_INSTRUCTION",
            "Render": "TTI_005_comp_dooh_6sec_v35.nk",
            "est.": "00:00:01",
            "Priority": "90"
        }
    ],
    "SUMMER_CLASSIC_JOZI": [
        {
            "Task_Progress": "100%",
            "Name": "TST_020_comp_v06",
            "Task_name": "TST_020_comp_v06.nk",
            "User": "stavile",
            "Plugin": "Nuke",
            "Progress": "90%",
            "Tasks": "(9/10)",
            "Status": "Rendering (1)",
            "Project": "SUMMER_CLASSIC_JOZI",
            "Render": "TST_020_comp_v06.nk",
            "est.": "00:00:01",
            "Priority": "90"
        },
        {
            "Task_Progress": "100%",
            "Name": "TST_055_Wheel_v1",
            "Task_name": "TST_055_Wheel_v18 - /out/main",
            "User": "hozhaev",
            "Plugin": "Houdini",
            "Progress": "93%",
            "Tasks": "(41/44)",
            "Status": "Rendering (3)",
            "Project": "SUMMER_CLASSIC_JOZI",
            "Render": "main",
            "est.": "00:00:01",
            "Priority": "60"
        }
    ],
    "WINLINE_BELARUS": [
        {
            "Task_Progress": "100%",
            "Name": "WLB_040_v11-/sta",
            "Task_name": "WLB_040_v11 - /stage/main/usdrender_rop",
            "User": "veber",
            "Plugin": "Houdini",
            "Progress": "15%",
            "Tasks": "(10/66)",
            "Status": "Rendering (9)",
            "Project": "WINLINE_BELARUS",
            "Render": "usdrender_rop",
            "est.": "03:40:07",
            "Priority": "60"
        },
        {
            "Task_Progress": "100%",
            "Name": "WLB_040_comp_v09",
            "Task_name": "WLB_040_comp_v09.nk",
            "User": "raznov",
            "Plugin": "Nuke",
            "Progress": "100%",
            "Tasks": "(66/66)",
            "Status": "Completed",
            "Project": "WINLINE_BELARUS",
            "Render": "WLB_040_comp_v09.nk",
            "est.": "00:00:00",
            "Priority": "90"
        },
        {
            "Task_Progress": "100%",
            "Name": "WLB_040_v11-/out",
            "Task_name": "WLB_040_v11 - /out/volume",
            "User": "veber",
            "Plugin": "Houdini",
            "Progress": "35%",
            "Tasks": "(5/14)",
            "Status": "Rendering (3)",
            "Project": "WINLINE_BELARUS",
            "Render": "volume",
            "est.": "00:57:45",
            "Priority": "75"
        },
        {
            "Task_Progress": "100%",
            "Name": "WLB_030_v013-/ou",
            "Task_name": "WLB_030_v013 - /out/uv",
            "User": "syslov",
            "Plugin": "Houdini",
            "Progress": "25%",
            "Tasks": "(2/8)",
            "Status": "Queued",
            "Project": "WINLINE_BELARUS",
            "Render": "uv",
            "est.": "unknown",
            "Priority": "65"
        },
        {
            "Task_Progress": "100%",
            "Name": "WLB_010_v44-/out",
            "Task_name": "WLB_010_v44 - /out/main_assemble",
            "User": "shashkov",
            "Plugin": "Houdini",
            "Progress": "86%",
            "Tasks": "(38/44)",
            "Status": "Rendering (6)",
            "Project": "WINLINE_BELARUS",
            "Render": "main_assemble",
            "est.": "00:00:01",
            "Priority": "60"
        }
    ],
    "CHERNOGOLOVKA_AI": [
        {
            "Task_Progress": "20%",
            "Name": "CHG_100_comp_v22",
            "Task_name": "CHG_100_comp_v22.nk",
            "User": "loktev",
            "Plugin": "Nuke",
            "Progress": "0%",
            "Tasks": "(0/26)",
            "Status": "Rendering (6)",
            "Project": "CHERNOGOLOVKA_AI",
            "Render": "CHG_100_comp_v22.nk",
            "est.": "unknown",
            "Priority": "90"
        },
        {
            "Task_Progress": "100%",
            "Name": "CHG_010_comp_v09",
            "Task_name": "CHG_010_comp_v09.nk",
            "User": "f.smirnov",
            "Plugin": "Nuke",
            "Progress": "97%",
            "Tasks": "(44/45)",
            "Status": "Rendering (1)",
            "Project": "CHERNOGOLOVKA_AI",
            "Render": "CHG_010_comp_v09.nk",
            "est.": "00:00:01",
            "Priority": "90"
        }
    ]
}