{
    "ACTIBIO": [
        {
            "Task_Progress": "100%",
            "Name": "AKB_120_v08-/out",
            "Task_name": "AKB_120_v08 - /out/1st_scene",
            "User": "shashkov",
            "Plugin": "Houdini",
            "Progress": "54%",
            "Tasks": "(26/48)",
            "Status": "Rendering (7)",
            "Project": "ACTIBIO",
            "Render": "1st_scene",
            "est.": "00:09:14",
            "Priority": "60"
        },
        {
            "Task_Progress": "100%",
            "Name": "AKB_120_v08-/out",
            "Task_name": "AKB_120_v08 - /out/woman",
            "User": "shashkov",
            "Plugin": "Houdini",
            "Progress": "98%",
            "Tasks": "(89/90)",
            "Status": "Rendering (1)",
            "Project": "ACTIBIO",
            "Render": "woman",
            "est.": "00:00:01",
            "Priority": "60"
        },
        {
            "Task_Progress": "100%",
            "Name": "AKB_120_v08-/out",
            "Task_name": "AKB_120_v08 - /out/2nd_scene",
            "User": "shashkov",
            "Plugin": "Houdini",
            "Progress": "88%",
            "Tasks": "(40/45)",
            "Status": "Rendering (5)",
            "Project": "ACTIBIO",
            "Render": "2nd_scene",
            "est.": "00:00:01",
            "Priority": "60"
        }
    ],
    "WINLINE_BELARUS": [
        {
            "Task_Progress": "33.33%",
            "Name": "WLB_040_v15-/out",
            "Task_name": "WLB_040_v15 - /out/volume",
            "User": "veber",
            "Plugin": "Houdini",
            "Progress": "0%",
            "Tasks": "(0/22)",
            "Status": "Rendering (7)",
            "Project": "WINLINE_BELARUS",
            "Render": "volume",
            "est.": "unknown",
            "Priority": "60"
        },
        {
            "Task_Progress": "12%",
            "Name": "WLB_040_v15-/sta",
            "Task_name": "WLB_040_v15 - /stage/main/usdrender_rop",
            "User": "veber",
            "Plugin": "Houdini",
            "Progress": "0%",
            "Tasks": "(0/66)",
            "Status": "Rendering (5)",
            "Project": "WINLINE_BELARUS",
            "Render": "usdrender_rop",
            "est.": "unknown",
            "Priority": "75"
        }
    ]
}