{
    "ADIDAS_DICKS_PRLM": [
        {
            "Task_Progress": "100%",
            "Name": "Generic_v153-/ob",
            "Task_name": "Generic_v153 - /obj/lopnet1/DSG_696_main/usdrender_rop",
            "User": "glavatskih",
            "Plugin": "Houdini",
            "Progress": "26%",
            "Tasks": "(33/123)",
            "Status": "Rendering (4)",
            "Project": "ADIDAS_DICKS_PRLM",
            "Render": "usdrender_rop",
            "est.": "10:44:37",
            "Priority": "60"
        },
        {
            "Task_Progress": "100%",
            "Name": "Generic_v154-/ob",
            "Task_name": "Generic_v154 - /obj/lopnet1/DSG_696_ground_atmo/usdrender_rop",
            "User": "glavatskih",
            "Plugin": "Houdini",
            "Progress": "25%",
            "Tasks": "(31/123)",
            "Status": "Rendering (4)",
            "Project": "ADIDAS_DICKS_PRLM",
            "Render": "usdrender_rop",
            "est.": "20:08:09",
            "Priority": "60"
        },
        {
            "Task_Progress": "100%",
            "Name": "Generic_v162d-/o",
            "Task_name": "Generic_v162d - /obj/lopnet1/DSG_640_main/usdrender_rop",
            "User": "glavatskih",
            "Plugin": "Houdini",
            "Progress": "25%",
            "Tasks": "(18/72)",
            "Status": "Rendering (4)",
            "Project": "ADIDAS_DICKS_PRLM",
            "Render": "usdrender_rop",
            "est.": "16:30:28",
            "Priority": "60"
        },
        {
            "Task_Progress": "100%",
            "Name": "Generic_v153-/ob",
            "Task_name": "Generic_v153 - /obj/lopnet1/DSG_696_crowd/usdrender_rop",
            "User": "glavatskih",
            "Plugin": "Houdini",
            "Progress": "67%",
            "Tasks": "(83/123)",
            "Status": "Rendering (4)",
            "Project": "ADIDAS_DICKS_PRLM",
            "Render": "usdrender_rop",
            "est.": "05:38:36",
            "Priority": "60"
        },
        {
            "Task_Progress": "100%",
            "Name": "Generic_v153-/ob",
            "Task_name": "Generic_v153 - /obj/lopnet1/DSG_680_crowd/usdrender_rop",
            "User": "glavatskih",
            "Plugin": "Houdini",
            "Progress": "98%",
            "Tasks": "(70/71)",
            "Status": "Rendering (1)",
            "Project": "ADIDAS_DICKS_PRLM",
            "Render": "usdrender_rop",
            "est.": "00:00:01",
            "Priority": "60"
        },
        {
            "Task_Progress": "100%",
            "Name": "Generic_v154-/ob",
            "Task_name": "Generic_v154 - /obj/lopnet1/DSG_520_ground_atmo/usdrender_rop",
            "User": "glavatskih",
            "Plugin": "Houdini",
            "Progress": "41%",
            "Tasks": "(75/179)",
            "Status": "Rendering (4)",
            "Project": "ADIDAS_DICKS_PRLM",
            "Render": "usdrender_rop",
            "est.": "12:08:31",
            "Priority": "60"
        },
        {
            "Task_Progress": "100%",
            "Name": "Generic_v153-/ob",
            "Task_name": "Generic_v153 - /obj/lopnet1/DSG_680_main/usdrender_rop",
            "User": "glavatskih",
            "Plugin": "Houdini",
            "Progress": "84%",
            "Tasks": "(60/71)",
            "Status": "Rendering (4)",
            "Project": "ADIDAS_DICKS_PRLM",
            "Render": "usdrender_rop",
            "est.": "01:31:47",
            "Priority": "60"
        },
        {
            "Task_Progress": "100%",
            "Name": "Generic_v154-/ob",
            "Task_name": "Generic_v154 - /obj/lopnet1/DSG_680_ground_atmo/usdrender_rop",
            "User": "glavatskih",
            "Plugin": "Houdini",
            "Progress": "38%",
            "Tasks": "(27/71)",
            "Status": "Rendering (4)",
            "Project": "ADIDAS_DICKS_PRLM",
            "Render": "usdrender_rop",
            "est.": "11:36:50",
            "Priority": "60"
        },
        {
            "Task_Progress": "100%",
            "Name": "Generic_v154-/ob",
            "Task_name": "Generic_v154 - /obj/lopnet1/DSG_680_main/usdrender_rop",
            "User": "glavatskih",
            "Plugin": "Houdini",
            "Progress": "90%",
            "Tasks": "(64/71)",
            "Status": "Rendering (4)",
            "Project": "ADIDAS_DICKS_PRLM",
            "Render": "usdrender_rop",
            "est.": "00:25:15",
            "Priority": "60"
        }
    ],
    "T2_INSTRUCTION": [
        {
            "Task_Progress": "100%",
            "Name": "TTI_015_v13-/obj",
            "Task_name": "TTI_015_v13 - /obj/lopnet_outdoor/main_plane/usdrender_rop",
            "User": "goncharov",
            "Plugin": "Houdini",
            "Progress": "98%",
            "Tasks": "(64/65)",
            "Status": "Rendering (1)",
            "Project": "T2_INSTRUCTION",
            "Render": "usdrender_rop",
            "est.": "00:00:01",
            "Priority": "65"
        },
        {
            "Task_Progress": "100%",
            "Name": "TTI_005_v93-/obj",
            "Task_name": "TTI_005_v93 - /obj/lopnet1/ground/usdrender_rop",
            "User": "goncharov",
            "Plugin": "Houdini",
            "Progress": "24%",
            "Tasks": "(45/186)",
            "Status": "Rendering (3)",
            "Project": "T2_INSTRUCTION",
            "Render": "usdrender_rop",
            "est.": "03:51:42",
            "Priority": "60"
        },
        {
            "Task_Progress": "0%",
            "Name": "TTI_040_comp_v20",
            "Task_name": "TTI_040_comp_v20.nk",
            "User": "lukyanova",
            "Plugin": "Nuke",
            "Progress": "0%",
            "Tasks": "(0/20)",
            "Status": "Queued",
            "Project": "T2_INSTRUCTION",
            "Render": "TTI_040_comp_v20.nk",
            "est.": "unknown",
            "Priority": "90"
        },
        {
            "Task_Progress": "100%",
            "Name": "TTI_005_v94-/obj",
            "Task_name": "TTI_005_v94 - /obj/lopnet1/airplane/usdrender_rop",
            "User": "goncharov",
            "Plugin": "Houdini",
            "Progress": "94%",
            "Tasks": "(88/93)",
            "Status": "Rendering (3)",
            "Project": "T2_INSTRUCTION",
            "Render": "usdrender_rop",
            "est.": "00:11:06",
            "Priority": "60"
        },
        {
            "Task_Progress": "100%",
            "Name": "TTI_005_v94-/obj",
            "Task_name": "TTI_005_v94 - /obj/lopnet1/ground/usdrender_rop",
            "User": "goncharov",
            "Plugin": "Houdini",
            "Progress": "10%",
            "Tasks": "(10/93)",
            "Status": "Rendering (3)",
            "Project": "T2_INSTRUCTION",
            "Render": "usdrender_rop",
            "est.": "15:03:43",
            "Priority": "60"
        },
        {
            "Task_Progress": "100%",
            "Name": "TTI_005_v92-/obj",
            "Task_name": "TTI_005_v92 - /obj/lopnet1/ground/usdrender_rop",
            "User": "goncharov",
            "Plugin": "Houdini",
            "Progress": "12%",
            "Tasks": "(24/186)",
            "Status": "Rendering (3)",
            "Project": "T2_INSTRUCTION",
            "Render": "usdrender_rop",
            "est.": "21:04:16",
            "Priority": "60"
        },
        {
            "Task_Progress": "100%",
            "Name": "TTI_005_v92-/obj",
            "Task_name": "TTI_005_v92 - /obj/lopnet1/airplane/usdrender_rop",
            "User": "goncharov",
            "Plugin": "Houdini",
            "Progress": "33%",
            "Tasks": "(63/186)",
            "Status": "Rendering (3)",
            "Project": "T2_INSTRUCTION",
            "Render": "usdrender_rop",
            "est.": "15:59:06",
            "Priority": "60"
        },
        {
            "Task_Progress": "100%",
            "Name": "TTI_005_v93-/obj",
            "Task_name": "TTI_005_v93 - /obj/lopnet1/airplane/usdrender_rop",
            "User": "goncharov",
            "Plugin": "Houdini",
            "Progress": "36%",
            "Tasks": "(67/186)",
            "Status": "Rendering (2)",
            "Project": "T2_INSTRUCTION",
            "Render": "usdrender_rop",
            "est.": "18:31:41",
            "Priority": "60"
        }
    ]
}