{
    "TUTORS": [
        {
            "Task_Progress": "0%",
            "Name": "Vellum_Scene_v09",
            "Task_name": "Vellum_Scene_v09 - /out/R_Fur",
            "User": "hozhaev",
            "Plugin": "Houdini",
            "Progress": "35%",
            "Tasks": "(71/201)",
            "Status": "Rendering (23)",
            "Project": "TUTORS",
            "Render": "R_Fur",
            "est.": "00:22:22",
            "Priority": "60"
        },
        {
            "Task_Progress": "24%",
            "Name": "Vellum_Scene_v09",
            "Task_name": "Vellum_Scene_v09 - /obj/Construct/Fur_R_rch/render",
            "User": "hozhaev",
            "Plugin": "Houdini",
            "Progress": "24%",
            "Tasks": "(0/1)",
            "Status": "Rendering (1)",
            "Project": "TUTORS",
            "Render": "render",
            "est.": "unknown",
            "Priority": "100"
        }
    ],
    "RICH_TEA_MULTON": [
        {
            "Task_Progress": "100%",
            "Name": "Rich_Tea_Multon_",
            "Task_name": "Rich_Tea_Multon_env_shading_v13 - /obj/lopnet1/main11/usdrender_rop",
            "User": "goncharov",
            "Plugin": "Houdini",
            "Progress": "48%",
            "Tasks": "(70/144)",
            "Status": "Rendering (25)",
            "Project": "RICH_TEA_MULTON",
            "Render": "usdrender_rop",
            "est.": "00:20:18",
            "Priority": "60"
        }
    ]
}